voicecode.cpython-39-darwin.so
voicecode_resource/1.icns
voicecode_resource/main.py
voicecode_resource/Easy_Code_pics/None.png
voicecode_resource/Easy_Code_pics/add.png
voicecode_resource/Easy_Code_pics/add_into.png
voicecode_resource/Easy_Code_pics/append.png
voicecode_resource/Easy_Code_pics/at_point.png
voicecode_resource/Easy_Code_pics/clear.png
voicecode_resource/Easy_Code_pics/contains.png
voicecode_resource/Easy_Code_pics/draw.png
voicecode_resource/Easy_Code_pics/drawBackground.png
voicecode_resource/Easy_Code_pics/drawForeground.png
voicecode_resource/Easy_Code_pics/end_.png
voicecode_resource/Easy_Code_pics/folder.png
voicecode_resource/Easy_Code_pics/from_house.png
voicecode_resource/Easy_Code_pics/from_json.png
voicecode_resource/Easy_Code_pics/from_py.png
voicecode_resource/Easy_Code_pics/from_rect.png
voicecode_resource/Easy_Code_pics/get_.png
voicecode_resource/Easy_Code_pics/height.png
voicecode_resource/Easy_Code_pics/index.png
voicecode_resource/Easy_Code_pics/insert.png
voicecode_resource/Easy_Code_pics/intersect.png
voicecode_resource/Easy_Code_pics/item.png
voicecode_resource/Easy_Code_pics/json_window.png
voicecode_resource/Easy_Code_pics/main_window.png
voicecode_resource/Easy_Code_pics/mouseDoubleClickEvent.png
voicecode_resource/Easy_Code_pics/mouseMoveEvent.png
voicecode_resource/Easy_Code_pics/mousePressEvent.png
voicecode_resource/Easy_Code_pics/mouseReleaseEvent.png
voicecode_resource/Easy_Code_pics/output_to_py.png
voicecode_resource/Easy_Code_pics/painter.png
voicecode_resource/Easy_Code_pics/path.png
voicecode_resource/Easy_Code_pics/pen.png
voicecode_resource/Easy_Code_pics/point.png
voicecode_resource/Easy_Code_pics/pos.png
voicecode_resource/Easy_Code_pics/position.png
voicecode_resource/Easy_Code_pics/program_window.png
voicecode_resource/Easy_Code_pics/rect.bottom.png
voicecode_resource/Easy_Code_pics/rect.bottomLeft.png
voicecode_resource/Easy_Code_pics/rect.bottomRight.png
voicecode_resource/Easy_Code_pics/rect.left.png
voicecode-0.0.1.dist-info/METADATA
voicecode-0.0.1.dist-info/WHEEL
voicecode-0.0.1.dist-info/entry_points.txt
voicecode-0.0.1.dist-info/top_level.txt
voicecode-0.0.1.dist-info/RECORD
