Metadata-Version: 2.1
Name: voicecode
Version: 0.0.1
Summary: voicecode project
Home-page: UNKNOWN
License: UNKNOWN
Platform: UNKNOWN
